chatbot_webraft/.google-cookie
chatbot_webraft/__init__.py
chatbot_webraft/chat.py
chatbot_webraft/chatbot.py
chatbot_webraft/code.csv
chatbot_webraft/generator.py
chatbot_webraft/models.py
chatbot_webraft/modeltype_load.py
chatbot_webraft/preprocess.py
chatbot_webraft/rxgenv.py
chatbot_webraft/sample.csv
chatbot_webraft/sample2.csv
chatbot_webraft/test.py
chatbot_webraft/test2.py
chatbot_webraft/train.py
chatbot_webraft/utils.py
chatbot_webraft/yourmodel.py
chatbot_webraft-1.0.2.dist-info/METADATA
chatbot_webraft-1.0.2.dist-info/WHEEL
chatbot_webraft-1.0.2.dist-info/licenses/LICENSE
chatbot_webraft-1.0.2.dist-info/RECORD
