Metadata-Version: 2.1
Name: chatbot_webraft
Version: 1.0.2
Summary: A package for building chatbots easily without needing of any high system resources.
Author-email: Webraft <team@webraft.in>
License: MIT License
License-File: LICENSE
Keywords: Artificial intelligence,ai,ai code,ai code generator,ai writer,bot,chat bot,chat bot library,chatbot,chatbotwebraft,chatgpt,chatter,code generator,code writer,generator,transformer,webraft
Classifier: License :: OSI Approved :: MIT License
Classifier: Operating System :: OS Independent
Classifier: Programming Language :: Python :: 3
Requires-Python: >=3.6
Requires-Dist: nltk
Requires-Dist: numpy
Requires-Dist: requests
Requires-Dist: sentence-transformers
Requires-Dist: torch
Requires-Dist: transformers
